README.txt
mycraaawler.py
setup.py
CesarValiente_MSWL_WebCrawler.egg-info/PKG-INFO
CesarValiente_MSWL_WebCrawler.egg-info/SOURCES.txt
CesarValiente_MSWL_WebCrawler.egg-info/dependency_links.txt
CesarValiente_MSWL_WebCrawler.egg-info/requires.txt
CesarValiente_MSWL_WebCrawler.egg-info/top_level.txt
pymycraaawler/CheckArguments.py
pymycraaawler/ConnectionManager.py
pymycraaawler/HtmlParser.py
pymycraaawler/Log.py
pymycraaawler/Settings.py
pymycraaawler/__init__.py