Metadata-Version: 1.0
Name: CesarValiente-MSWL-WebCrawler
Version: 1.0
Summary: WebCrawler for the  Development & Tools subject of the M.Sc. on Free Software
Home-page: https://github.com/CesarValiente/FLOSS
Author: Cesar Valiente Gordo
Author-email: cesar.valiente@gmail.com
License: GNU GPLv3
Download-URL: http://pypi.python.org/pypi/MyCraaawler/1.0
Keywords: webcrawler
Platform: UNKNOWN
